setup.py
ipsedixit/__init__.py
ipsedixit/caesar.txt
ipsedixit/markov.py
ipsedixit/meta.py
ipsedixit/tacitus.txt
ipsedixit.egg-info/PKG-INFO
ipsedixit.egg-info/SOURCES.txt
ipsedixit.egg-info/dependency_links.txt
ipsedixit.egg-info/entry_points.txt
ipsedixit.egg-info/not-zip-safe
ipsedixit.egg-info/top_level.txt