Metadata-Version: 1.1
Name: ipsedixit
Version: 0.9.0
Summary: Lorem ipsum on steroids.
Home-page: https://github.com/dmulholland/ipsedixit
Author: Darren Mulholland
Author-email: UNKNOWN
License: Public Domain
Platform: UNKNOWN
Classifier: Programming Language :: Python :: 3
Classifier: Development Status :: 5 - Production/Stable
Classifier: Operating System :: OS Independent
Classifier: License :: Public Domain
Classifier: Intended Audience :: Developers
